django_yarnpkg/__init__.py
django_yarnpkg/conf.py
django_yarnpkg/context_processors.py
django_yarnpkg/exceptions.py
django_yarnpkg/finders.py
django_yarnpkg/models.py
django_yarnpkg/shortcuts.py
django_yarnpkg/test_settings.py
django_yarnpkg/yarn.py
django_yarnpkg/management/__init__.py
django_yarnpkg/management/base.py
django_yarnpkg/management/commands/__init__.py
django_yarnpkg/management/commands/yarn.py
django_yarnpkg/management/commands/yarn_install.py
django_yarnpkg/templatetags/__init__.py
django_yarnpkg/templatetags/yarn.py
django_yarnpkg/tests/__init__.py
django_yarnpkg/tests/base.py
django_yarnpkg/tests/test_finders.py
django_yarnpkg/tests/test_yarn.py
django_yarnpkg-6.1.3.dist-info/LICENSE
django_yarnpkg-6.1.3.dist-info/METADATA
django_yarnpkg-6.1.3.dist-info/WHEEL
django_yarnpkg-6.1.3.dist-info/top_level.txt
django_yarnpkg-6.1.3.dist-info/zip-safe
django_yarnpkg-6.1.3.dist-info/RECORD
