Metadata-Version: 2.1
Name: django-yarnpkg
Version: 6.1.3
Summary: Integrate django with yarnpkg
Home-page: https://edugit.org/AlekSIS/libs/django-yarnpkg
Author: Dominik George
Author-email: nik@naturalnet.de
License: Apache-2.0
Classifier: Framework :: Django
Classifier: Programming Language :: JavaScript
Classifier: Programming Language :: Python
Classifier: Programming Language :: Python :: 3
License-File: LICENSE
Requires-Dist: django
